scripts/__init__.py
scripts/cli.py
scripts/download.py
scripts/fullmetadata.py
scripts/metadata.py
srahunter-0.0.2.dist-info/LICENSE
srahunter-0.0.2.dist-info/METADATA
srahunter-0.0.2.dist-info/WHEEL
srahunter-0.0.2.dist-info/entry_points.txt
srahunter-0.0.2.dist-info/top_level.txt
srahunter-0.0.2.dist-info/RECORD
