Metadata-Version: 2.1
Name: srahunter
Version: 0.0.2
Summary: A tool for processing SRA accessions
Home-page: https://github.com/GitEnricoNeko/SRAHunter
Author: Bortoletto Enrico
Author-email: enricobortoletto30@gmail.com
Classifier: Development Status :: 4 - Beta
Classifier: Intended Audience :: Science/Research
Classifier: License :: OSI Approved :: MIT License
Classifier: Programming Language :: Python :: 3
Classifier: Programming Language :: Python :: 3.6
Classifier: Programming Language :: Python :: 3.7
Classifier: Programming Language :: Python :: 3.8
Classifier: Programming Language :: Python :: 3.9
Classifier: Programming Language :: Python :: 3.10
Classifier: Programming Language :: Python :: 3.11
Classifier: Programming Language :: Python :: 3.12
Classifier: Operating System :: OS Independent
Requires-Python: >=3.6
License-File: LICENSE
Requires-Dist: pandas >=2.0.2
Requires-Dist: psutil >=5.7
Requires-Dist: pyfiglet ==1.0.2
Requires-Dist: requests ==2.31.0
Requires-Dist: tqdm ==4.66.1
